CommandLineTool/__init__.py
CommandLineTool/script.py
DNS_Command_Line_Tool-1.0.0.dist-info/LICENSE.txt
DNS_Command_Line_Tool-1.0.0.dist-info/METADATA
DNS_Command_Line_Tool-1.0.0.dist-info/WHEEL
DNS_Command_Line_Tool-1.0.0.dist-info/entry_points.txt
DNS_Command_Line_Tool-1.0.0.dist-info/top_level.txt
DNS_Command_Line_Tool-1.0.0.dist-info/RECORD
