Metadata-Version: 2.1
Name: DNS-Command-Line-Tool
Version: 1.0.0
Summary: UNKNOWN
Home-page: UNKNOWN
Author: Vinuri Bandara
Author-email: vinurib@scorelab.org
License: MIT
Keywords: DNSIP cmd update
Platform: UNKNOWN
Classifier: Programming Language :: Python :: 3
Classifier: License :: OSI Approved :: MIT License
Classifier: Operating System :: OS Independent
License-File: LICENSE.txt
Requires-Dist: APScheduler (==3.7.0)
Requires-Dist: cachetools (==4.2.2)
Requires-Dist: certifi (==2021.5.30)
Requires-Dist: cffi (==1.14.6)
Requires-Dist: charset-normalizer (==2.0.4)
Requires-Dist: google-api-core (==1.31.1)
Requires-Dist: google-auth (==1.34.0)
Requires-Dist: google-cloud-core (==1.7.2)
Requires-Dist: google-cloud-storage (==1.41.1)
Requires-Dist: google-crc32c (==1.1.2)
Requires-Dist: google-resumable-media (==1.3.3)
Requires-Dist: googleapis-common-protos (==1.53.0)
Requires-Dist: idna (==3.2)
Requires-Dist: packaging (==21.0)
Requires-Dist: protobuf (==3.17.3)
Requires-Dist: pyasn1 (==0.4.8)
Requires-Dist: pyasn1-modules (==0.2.8)
Requires-Dist: pycparser (==2.20)
Requires-Dist: pyparsing (==2.4.7)
Requires-Dist: pytz (==2021.1)
Requires-Dist: requests (==2.26.0)
Requires-Dist: rsa (==4.7.2)
Requires-Dist: six (==1.16.0)
Requires-Dist: tzlocal (==2.1)
Requires-Dist: urllib3 (==1.26.6)
